aix_caller/__init__.py
aix_caller/module.py
aix_caller-0.1.0.dist-info/LICENSE
aix_caller-0.1.0.dist-info/METADATA
aix_caller-0.1.0.dist-info/WHEEL
aix_caller-0.1.0.dist-info/top_level.txt
aix_caller-0.1.0.dist-info/RECORD
